lifestay/__init__.py
lifestay/examples/__init__.py
lifestay/examples/survival_examples.py
lifestay/loader/csv_processor.py
lifestay/loader/load_csv.py
lifestay/loader/log_utils.py
lifestay/loader/sample_builder.py
lifestay/samplers/__init__.py
lifestay/samplers/eol_extractor.py
lifestay/samplers/log_utils.py
lifestay/samplers/window_averager.py
lifestay/survival/__init__.py
lifestay/survival/basic_cox.py
lifestay/survival/comprehensive_visualization.py
lifestay/survival/contribution_analysis.py
lifestay/survival/cox_model.py
lifestay/survival/data_builder.py
lifestay/survival/data_converter.py
lifestay/survival/fusion_score.py
lifestay/survival/interaction_cox.py
lifestay/survival/metrics_calculation.py
lifestay/survival/risk_comparison_visualization.py
lifestay/survival/risk_stratification.py
lifestay/survival/test_survival.py
lifestay/survival/utils.py
lifestay-0.1.0.dist-info/LICENSE
lifestay-0.1.0.dist-info/METADATA
lifestay-0.1.0.dist-info/WHEEL
lifestay-0.1.0.dist-info/RECORD
